liqpay_manager-0.0.2.dist-info/DESCRIPTION.rst
liqpay_manager-0.0.2.dist-info/METADATA
liqpay_manager-0.0.2.dist-info/RECORD
liqpay_manager-0.0.2.dist-info/WHEEL
liqpay_manager-0.0.2.dist-info/entry_points.txt
liqpay_manager-0.0.2.dist-info/metadata.json
liqpay_manager-0.0.2.dist-info/top_level.txt
lq_mgr/__init__.py
lq_mgr/__main__.py
lq_mgr/cli.py
lq_mgr/manager.py
