Metadata-Version: 2.0
Name: liqpay-manager
Version: 0.0.2
Summary: Truly Pythonic CLI for managing LiqPay via its API
Home-page: https://github.com/webknjaz/lq-mgr
Author: Sviatoslav Sydorenko
Author-email: wk+github-open-source@sydorenko.org.ua
License: MIT
Keywords: CLI,tool,API,client,LiqPay
Platform: UNKNOWN
Classifier: Development Status :: 3 - Alpha
Classifier: Intended Audience :: Developers
Classifier: License :: OSI Approved :: MIT License
Classifier: Operating System :: OS Independent
Classifier: Programming Language :: Python :: Implementation :: CPython
Classifier: Programming Language :: Python
Classifier: Programming Language :: Python :: 3
Classifier: Programming Language :: Python :: 3 :: Only
Classifier: Programming Language :: Python :: 3.6
Classifier: Programming Language :: Python :: Implementation :: CPython
Classifier: Programming Language :: Python :: Implementation :: PyPy
Classifier: Topic :: Internet :: WWW/HTTP
Requires-Python: >=3.6
Requires-Dist: click
Requires-Dist: envparse
Requires-Dist: liqpay-python3
